LICENSE
README.md
setup.py
yascikit_learn.egg-info/PKG-INFO
yascikit_learn.egg-info/SOURCES.txt
yascikit_learn.egg-info/dependency_links.txt
yascikit_learn.egg-info/requires.txt
yascikit_learn.egg-info/top_level.txt
yasklearn/__init__.py
yasklearn/naive_bayes.py
yasklearn/cluster/__init__.py
yasklearn/cluster/k_medoids.py
yasklearn/cluster/x_medoids.py
yasklearn/cluster/xmeans.py
yasklearn/decomposition/__init__.py
yasklearn/decomposition/plsa.py
yasklearn/decomposition/plsv.py
yasklearn/ftrl_proximal/__init__.py
yasklearn/ftrl_proximal/ftrl_proximal.py
yasklearn/ftrl_proximal/ftrl_proximal_regressor.py
yasklearn/model_selection/__init__.py
yasklearn/model_selection/_split.py