Metadata-Version: 2.1
Name: yascikit-learn
Version: 0.1.3
Summary: Yet another scikit-learn
Home-page: https://github.com/ikegami-yukino/yascikit-learn
Author: Yukino Ikegami
Author-email: yknikgm@gmail.com
License: MIT License
Keywords: Machine Learning
Classifier: Development Status :: 2 - Pre-Alpha
Classifier: Intended Audience :: Developers
Classifier: Intended Audience :: Science/Research
Classifier: License :: OSI Approved :: MIT License
Classifier: Programming Language :: Python :: 3.8
Classifier: Programming Language :: Python :: 3.9
Classifier: Programming Language :: Python :: 3.10
License-File: LICENSE
